[1,["36QuZ7EzdG5q9kbJKpUg8+","0cev4g2+RJmIWC37gBjQ6a","5dPta/7cRIVbyCxT9Eq9G/","dbT/TTc7lC4LnUchPCdaGM","16xEV5GMZFo4IDrtfR66UI","aagsCEhOpINY6DaLTJJn18","08fdW2LVVLxILhr5Voz15t","55M7gng8NJGrWXapqZVGPW","afh/l6kI5JMYSvoamoMjVi","b4C0Su4ZtPJoPccFP6bz2I","27Lm/kUrRJdJt2aK/Nbt0V","4bS3eAKdBLWZOMy+qAIqIv","0dOiMWnRdDh6QgtvgCmu3V","f5bWtdfiRJ8qMnTG8DBeoB","55ZYXAWEpJIbpRA18Mdv9s"],["_textureSetter","bonus_respin_multiplier","bonus_respin_win_5_sym","bw","collect","info_1","info_2","info_3","info_4","info_total_win","mw","smw","spin","total_win","win"],["cc.SpriteFrame",["cc.SpriteAtlas",["_name","_spriteFrames"],2,11]],[[1,0,1,2]],[[[{"name":"info_2","rect":[555,95,684,69],"offset":[0,-1],"originalSize":[690,71],"capInsets":[0,0,0,0]}],[0],0,[0],[0],[0]],[[{"name":"bonus_respin_multiplier","rect":[1241,151,504,251],"offset":[0,0],"originalSize":[504,251],"capInsets":[0,0,0,0]}],[0],0,[0],[0],[0]],[[{"name":"spin","rect":[1747,151,111,47],"offset":[0,0],"originalSize":[111,47],"rotated":1,"capInsets":[0,0,0,0]}],[0],0,[0],[0],[0]],[[{"name":"collect","rect":[1475,1,237,54],"offset":[0,0],"originalSize":[237,54],"capInsets":[0,0,0,0]}],[0],0,[0],[0],[0]],[[{"name":"mw","rect":[555,166,567,148],"offset":[0,0],"originalSize":[567,148],"capInsets":[0,0,0,0]}],[0],0,[0],[0],[0]],[[{"name":"smw","rect":[1,95,552,221],"offset":[0,0],"originalSize":[552,221],"capInsets":[0,0,0,0]}],[0],0,[0],[0],[0]],[[{"name":"info_3","rect":[1,1,1472,41],"offset":[-1,-1],"originalSize":[1480,71],"capInsets":[0,0,0,0]}],[0],0,[0],[0],[0]],[[{"name":"win","rect":[1241,95,92,45],"offset":[0,0],"originalSize":[92,45],"capInsets":[0,0,0,0]}],[0],0,[0],[0],[0]],[[{"name":"bonus_respin_win_5_sym","rect":[1,318,577,135],"offset":[0,0],"originalSize":[577,135],"capInsets":[0,0,0,0]}],[0],0,[0],[0],[0]],[[{"name":"info_1","rect":[1057,404,630,67],"offset":[-4,-1],"originalSize":[644,71],"capInsets":[0,0,0,0]}],[0],0,[0],[0],[0]],[[{"name":"info_4","rect":[1,44,1345,49],"offset":[-1,2],"originalSize":[1351,71],"capInsets":[0,0,0,0]}],[0],0,[0],[0],[0]],[[{"name":"info_total_win","rect":[1124,166,114,68],"offset":[0,0],"originalSize":[114,68],"capInsets":[0,0,0,0]}],[0],0,[0],[0],[0]],[[{"name":"bw","rect":[580,316,475,147],"offset":[0,0],"originalSize":[475,147],"capInsets":[0,0,0,0]}],[0],0,[0],[0],[0]],[[[0,"general.plist",[{},"bonus_respin_multiplier",6,0,"bonus_respin_win_5_sym",6,1,"bw",6,2,"collect",6,3,"info_1",6,4,"info_2",6,5,"info_3",6,6,"info_4",6,7,"info_total_win",6,8,"mw",6,9,"smw",6,10,"spin",6,11,"total_win",6,12,"win",6,13]]],0,0,[0,0,0,0,0,0,0,0,0,0,0,0,0,0],[1,2,3,4,5,6,7,8,9,10,11,12,13,14],[1,2,3,4,5,6,7,8,9,10,11,12,13,14]],[[{"name":"total_win","rect":[1348,57,456,92],"offset":[0,0],"originalSize":[456,92],"capInsets":[0,0,0,0]}],[0],0,[0],[0],[0]]]]