[1,["b30WRKke5COpMVyh1v3sZu","89R0IVhaNGo4KNEwCxowuA","00ZSeC/FxEIa3yBTMUQ+6m"],["_textureSetter","info_tw","info_win"],["cc.SpriteFrame",["cc.SpriteAtlas",["_name","_spriteFrames"],2,11]],[[1,0,1,2]],[[[{"name":"info_win","rect":[1,69,119,40],"offset":[0,2],"originalSize":[129,84],"capInsets":[0,0,0,0]}],[0],0,[0],[0],[0]],[[{"name":"info_tw","rect":[1,1,120,66],"offset":[-1,0],"originalSize":[128,84],"capInsets":[0,0,0,0]}],[0],0,[0],[0],[0]],[[[0,"info_win_text.plist",[{},"info_tw",6,0,"info_win",6,1]]],0,0,[0,0],[1,2],[1,2]]]]