[1,["d5jWuqRTBB/4uBig0laHXg","53i/taEP9DZYgB4W+yCgz+","eedU2SzzJBBoOXaSeExxlc","a8ULrhIsxN6ZS6bnYsytSc","83mGkQ9WtO4a/BPSfBZX8n","d8M07YzBJMPZ9+CVJfR+93","82wCFZGjhOnJU1E3FG2qb5","e3EkRmENtO7quK4NvkWHM9","8fOl7JyxZPyqUKL9smv9o3","49WHLkNTpPxLJonvYF1pFl","19I5UBf8VBBJol0G38jXkb","75pA+GF9REy69NEJbMpGNI","c7cFuxbRJJ1qovPguGPhQI","aaduHkarlM65lPpHlu/kiM","00ZFp2vHBMO4isZuCOILGE","f9OzOmVP5O8ppnsFEiBc0+","fdz+Ct0NpCPoCxc2c8bR/v","dd+rg4pMJOz44MbGpa6SKD","d2y8MvwR9MHK3C0WzFdgyw","c1t6I4GwFNXqqQnol1Ja/q","87O8TH3htBw59WErWEv3yk","f2PIlRqmtLAKAs//o5mJKh","4f1Y5rKD9CfpQTbzMF5DX7","d2lijUdpVC9ajqkr4iLM8u","84jZSha8FGSZPx3AJBF/iK","52eC7vu2lFQaACbSDGcE3X","fcbem0eFND+ZpgDWfYjSwl","70QjGprk5EUZoHJaGHCq/k","16CvKqEVNL5IOhsOogYHpS"],["_textureSetter","h_candy","h_candy_blur","h_chocolate","h_chocolate_blur","h_reindeer","h_reindeer_blur","h_sock","h_sock_blur","l_a","l_a_blur","l_j","l_j_blur","l_k","l_k_blur","l_q","l_q_blur","s_2x","s_2x_blur","s_4x","s_4x_blur","s_5x","s_5x_blur","s_freespin","s_freespin_blur","s_gift","s_gift_blur","s_scatter","s_scatter_blur"],["cc.SpriteFrame",["cc.SpriteAtlas",["_name","_spriteFrames"],2,11]],[[1,0,1,2]],[[[{"name":"l_k_blur","rect":[333,207,91,129],"offset":[0,0],"originalSize":[175,175],"rotated":1,"capInsets":[0,0,0,0]}],[0],0,[0],[0],[0]],[[{"name":"s_scatter_blur","rect":[1,1,163,503],"offset":[-5,11],"originalSize":[175,525],"capInsets":[0,0,0,0]}],[0],0,[0],[0],[0]],[[{"name":"l_a_blur","rect":[333,104,101,129],"offset":[-1,0],"originalSize":[175,175],"rotated":1,"capInsets":[0,0,0,0]}],[0],0,[0],[0],[0]],[[[0,"symbol_packed_1.plist",[{},"h_candy",6,0,"h_candy_blur",6,1,"h_chocolate",6,2,"h_chocolate_blur",6,3,"h_reindeer",6,4,"h_reindeer_blur",6,5,"h_sock",6,6,"h_sock_blur",6,7,"l_a",6,8,"l_a_blur",6,9,"l_j",6,10,"l_j_blur",6,11,"l_k",6,12,"l_k_blur",6,13,"l_q",6,14,"l_q_blur",6,15,"s_2x",6,16,"s_2x_blur",6,17,"s_4x",6,18,"s_4x_blur",6,19,"s_5x",6,20,"s_5x_blur",6,21,"s_freespin",6,22,"s_freespin_blur",6,23,"s_gift",6,24,"s_gift_blur",6,25,"s_scatter",6,26,"s_scatter_blur",6,27]]],0,0,[0,0,0,0,0,0,0,0,0,0,0,0,0,0,0,0,0,0,0,0,0,0,0,0,0,0,0,0],[1,2,3,4,5,6,7,8,9,10,11,12,13,14,15,16,17,18,19,20,21,22,23,24,25,26,27,28],[1,2,3,4,5,6,7,8,9,10,11,12,13,14,15,16,17,18,19,20,21,22,23,24,25,26,27,28]],[[{"name":"s_5x_blur","rect":[462,342,155,95],"offset":[-1,0],"originalSize":[175,175],"rotated":1,"capInsets":[0,0,0,0]}],[0],0,[0],[0],[0]],[[{"name":"s_gift","rect":[626,247,145,145],"offset":[0,0],"originalSize":[175,175],"capInsets":[0,0,0,0]}],[0],0,[0],[0],[0]],[[{"name":"s_scatter","rect":[166,1,165,501],"offset":[-5,12],"originalSize":[175,525],"capInsets":[0,0,0,0]}],[0],0,[0],[0],[0]],[[{"name":"h_reindeer_blur","rect":[323,504,139,169],"offset":[1,0],"originalSize":[175,175],"capInsets":[0,0,0,0]}],[0],0,[0],[0],[0]],[[{"name":"h_chocolate_blur","rect":[333,300,127,155],"offset":[0,0],"originalSize":[175,175],"capInsets":[0,0,0,0]}],[0],0,[0],[0],[0]],[[{"name":"s_freespin_blur","rect":[162,506,159,175],"offset":[-1,0],"originalSize":[175,175],"capInsets":[0,0,0,0]}],[0],0,[0],[0],[0]],[[{"name":"s_4x_blur","rect":[467,148,159,95],"offset":[0,0],"originalSize":[175,175],"capInsets":[0,0,0,0]}],[0],0,[0],[0],[0]],[[{"name":"h_sock_blur","rect":[636,1,103,151],"offset":[0,0],"originalSize":[175,175],"rotated":1,"capInsets":[0,0,0,0]}],[0],0,[0],[0],[0]],[[{"name":"l_j_blur","rect":[559,342,65,133],"offset":[1,0],"originalSize":[175,175],"capInsets":[0,0,0,0]}],[0],0,[0],[0],[0]],[[{"name":"s_freespin","rect":[1,506,159,175],"offset":[-1,0],"originalSize":[175,175],"capInsets":[0,0,0,0]}],[0],0,[0],[0],[0]],[[{"name":"s_2x_blur","rect":[467,245,157,95],"offset":[-1,0],"originalSize":[175,175],"capInsets":[0,0,0,0]}],[0],0,[0],[0],[0]],[[{"name":"h_candy_blur","rect":[1,683,105,143],"offset":[0,0],"originalSize":[175,175],"rotated":1,"capInsets":[0,0,0,0]}],[0],0,[0],[0],[0]],[[{"name":"s_gift_blur","rect":[467,1,167,145],"offset":[-1,0],"originalSize":[175,175],"capInsets":[0,0,0,0]}],[0],0,[0],[0],[0]],[[{"name":"l_q_blur","rect":[146,683,105,129],"offset":[0,0],"originalSize":[175,175],"rotated":1,"capInsets":[0,0,0,0]}],[0],0,[0],[0],[0]]]]