[1,["82EOC7lM1H/qIVNKgFLTMi","6cDmSWS4hMTZkRTl+xs9Im","2bRNrc2SVDRrnLlKx4tVAH","e6PJglVvVOvo/XsT744l21"],["_textureSetter","text_collect","title_congrats","title_total_win"],["cc.SpriteFrame",["cc.SpriteAtlas",["_name","_spriteFrames"],2,11]],[[1,0,1,2]],[[[{"name":"title_congrats","rect":[50,261,442,113],"offset":[0,0],"originalSize":[442,113],"capInsets":[0,0,0,0]}],[0],0,[0],[0],[0]],[[{"name":"text_collect","rect":[0,0,328,50],"offset":[0,0],"originalSize":[328,50],"rotated":1,"capInsets":[0,0,0,0]}],[0],0,[0],[0],[0]],[[[0,"total_win.plist",[{},"text_collect",6,0,"title_congrats",6,1,"title_total_win",6,2]]],0,0,[0,0,0],[1,2,3],[1,2,3]],[[{"name":"title_total_win","rect":[50,0,522,261],"offset":[0,0],"originalSize":[522,261],"capInsets":[0,0,0,0]}],[0],0,[0],[0],[0]]]]