[1,["91Wg3qTtlDPpLaVe1rq9We"],["_textureSetter"],["cc.SpriteFrame"],0,[[[{"name":"hand_tap_19","rect":[1212,414,208,250],"offset":[-166,-120],"originalSize":[686,562],"rotated":1,"capInsets":[0,0,0,0]}],[0],0,[0],[0],[0]],[[{"name":"hand_tap_15","rect":[1398,0,206,232],"offset":[-166,-129],"originalSize":[686,562],"rotated":1,"capInsets":[0,0,0,0]}],[0],0,[0],[0],[0]],[[{"name":"hand_tap_17","rect":[0,206,206,234],"offset":[-166,-128],"originalSize":[686,562],"rotated":1,"capInsets":[0,0,0,0]}],[0],0,[0],[0],[0]],[[{"name":"hand_tap_14","rect":[980,414,208,232],"offset":[-166,-129],"originalSize":[686,562],"rotated":1,"capInsets":[0,0,0,0]}],[0],0,[0],[0],[0]],[[{"name":"hand_tap_00","rect":[0,0,206,232],"offset":[-166,-129],"originalSize":[686,562],"rotated":1,"capInsets":[0,0,0,0]}],[0],0,[0],[0],[0]],[[{"name":"hand_tap_04","rect":[1180,206,208,254],"offset":[-166,-118],"originalSize":[686,562],"rotated":1,"capInsets":[0,0,0,0]}],[0],0,[0],[0],[0]],[[{"name":"hand_tap_06","rect":[1686,206,208,232],"offset":[-166,-129],"originalSize":[686,562],"rotated":1,"capInsets":[0,0,0,0]}],[0],0,[0],[0],[0]],[[{"name":"hand_tap_07","rect":[700,0,206,232],"offset":[-166,-129],"originalSize":[686,562],"rotated":1,"capInsets":[0,0,0,0]}],[0],0,[0],[0],[0]],[[{"name":"hand_tap_23","rect":[706,206,206,232],"offset":[-166,-129],"originalSize":[686,562],"rotated":1,"capInsets":[0,0,0,0]}],[0],0,[0],[0],[0]],[[{"name":"hand_tap_02","rect":[464,0,206,236],"offset":[-166,-127],"originalSize":[686,562],"rotated":1,"capInsets":[0,0,0,0]}],[0],0,[0],[0],[0]],[[{"name":"hand_tap_22","rect":[474,206,206,232],"offset":[-166,-129],"originalSize":[686,562],"rotated":1,"capInsets":[0,0,0,0]}],[0],0,[0],[0],[0]],[[{"name":"hand_tap_16","rect":[1630,0,206,232],"offset":[-166,-129],"originalSize":[686,562],"rotated":1,"capInsets":[0,0,0,0]}],[0],0,[0],[0],[0]],[[{"name":"hand_tap_10","rect":[0,412,208,238],"offset":[-166,-126],"originalSize":[686,562],"rotated":1,"capInsets":[0,0,0,0]}],[0],0,[0],[0],[0]],[[{"name":"hand_tap_21","rect":[1714,414,208,232],"offset":[-166,-129],"originalSize":[686,562],"rotated":1,"capInsets":[0,0,0,0]}],[0],0,[0],[0],[0]],[[{"name":"hand_tap_11","rect":[238,412,208,244],"offset":[-166,-123],"originalSize":[686,562],"rotated":1,"capInsets":[0,0,0,0]}],[0],0,[0],[0],[0]],[[{"name":"hand_tap_18","rect":[234,206,206,240],"offset":[-166,-125],"originalSize":[686,562],"rotated":1,"capInsets":[0,0,0,0]}],[0],0,[0],[0],[0]],[[{"name":"hand_tap_09","rect":[1164,0,206,234],"offset":[-166,-128],"originalSize":[686,562],"rotated":1,"capInsets":[0,0,0,0]}],[0],0,[0],[0],[0]],[[{"name":"hand_tap_01","rect":[232,0,206,232],"offset":[-166,-129],"originalSize":[686,562],"rotated":1,"capInsets":[0,0,0,0]}],[0],0,[0],[0],[0]],[[{"name":"hand_tap_03","rect":[938,206,208,242],"offset":[-166,-124],"originalSize":[686,562],"rotated":1,"capInsets":[0,0,0,0]}],[0],0,[0],[0],[0]],[[{"name":"hand_tap_13","rect":[740,414,208,240],"offset":[-165,-125],"originalSize":[686,562],"rotated":1,"capInsets":[0,0,0,0]}],[0],0,[0],[0],[0]],[[{"name":"hand_tap_20","rect":[1462,414,208,252],"offset":[-165,-119],"originalSize":[686,562],"rotated":1,"capInsets":[0,0,0,0]}],[0],0,[0],[0],[0]],[[{"name":"hand_tap_08","rect":[932,0,206,232],"offset":[-166,-129],"originalSize":[686,562],"rotated":1,"capInsets":[0,0,0,0]}],[0],0,[0],[0],[0]],[[{"name":"hand_tap_05","rect":[1434,206,208,252],"offset":[-165,-119],"originalSize":[686,562],"rotated":1,"capInsets":[0,0,0,0]}],[0],0,[0],[0],[0]],[[{"name":"hand_tap_12","rect":[482,412,208,258],"offset":[-165,-116],"originalSize":[686,562],"rotated":1,"capInsets":[0,0,0,0]}],[0],0,[0],[0],[0]]]]