[1,["ecpdLyjvZBwrvm+cedCcQy","5ag1w82i5J451T78nRDVFV","f8StXvn5ZB6rb585nth7Qc","19OS+6J6BHR64M7cMAQQp6","6bg3u/Kp9CdLijsRRoTnam","84EUG89GVPBaxmpoehoCeI","38hS7KGthADrFoK5wW/tSa","58gcfx8TVJ9b2xiDhAn25N","f7V4NXANRDm6Ni4staHWGj","66scwN6w5E0b4r0sjQsy1+","f2IP7gLtpB8J9UM8AetNji","66CF6O1clLjrdxUYUlk9MT","95KYYDaSlGkYm8qx7DyJEn","d2zabHin1EhZZWoI3OJ7iF","67hKpiCl1Jc7uURCT9+7t/","46uR9Ny/ZK0ox9PxvOmcKa","1dfKXwH6VBG6MZH3r7pS34","0fMpEdqppBWqmrx1pWsOVW","12U6JrCslP4qjjUM1hNwwC","3bO78+0XFDNb9kyEzwOt64","a7wXev91BJH5UCXd/8B1BB","013HDw40pBxKfDQF8rHNFL","89az3G0fRJ4aWncu111KGi","bfWTUNZdhA3byJYj5Bf40x","41NBm7slJC9ZO/53iOG+8P","96wFdt+OlPP5apmfUuu4dn","491PLlirhPnaaM3K6YxoXJ","34/tNY6CBH9LN5+5C6FR6s","724iyChWNHWYzksQ9NBDXM","654Les3oJL+7P+ObD/KhHu","d5jtcNXAJCeKbqUVQPdCqv","d81MRORtZA645svenh2pBH","2el2bxFYhHcI1ykMpUZuH8","eb+vRc0xFOUa+HHqnDGq/e","58WYgiqIFCO4jpZaXb2iHY","1bZSepILhCsbjoQS8wJh+5","dc68Ff9LVIxL5mmuq6aB2O","a2wygWyLNCIoq11Xw81ZC6","0eUHNguORCe4X6f8uM9PbM"],["node","_spriteFrame","_textureSetter","root","wildParticleANode","blFgNode","blCharNode","blVfxC2Node","blVfxC1Node","blVfxBNode","blVfxANode","bgNode","frontEffectHolder","backEffectHolder","buttonHover","freeSpinDesc","startButtonSprite","freeSpinWon","loadingNumberRollingNode","loadingCircleNode","loadingHolderNode","textHolderNode","backgroundNode","freeSpinCountNode","startButton","startButtonNode","displayController","numberContainer","data","_parent","particlePrefab"],[["cc.Node",["_name","_opacity","_active","_prefab","_parent","_components","_contentSize","_trs","_children","_eulerAngles","_color"],0,4,1,9,5,7,2,5,5],"cc.SpriteFrame",["cc.Sprite",["_sizeMode","_isTrimmedMode","_dstBlendFactor","_srcBlendFactor","node","_materials","_spriteFrame"],-1,1,3,6],["cc.Node",["_name","_opacity","_parent","_components","_prefab","_contentSize","_trs","_children","_anchorPoint"],1,1,2,4,5,7,2,5],["cc.PrefabInfo",["fileId","root","asset"],2,1,1],["e13cc9FLShL66GevrFVSv5p",["maxContainerSize","enableComma","enableDecimal","numberSpriteAtlas","numberBlurSpriteAtlas","nodeNumberWidth","commaWidth","commaScale","decimalWidth","decimalScale","decimalNumberWidth","decimalNumberScale","multiplySpriteWidth","multiplySpriteScale","nodeNumberScale","blurScale","node","numberContainer","numberSprite"],-13,1,1,3],["cc.Prefab",["_name"],2],["cc.Node",["_name","_components","_prefab","_contentSize"],2,12,4,5],["608baPWdipJ966Y0+pwFNWK",["node","startButtonNode","startButton","freeSpinCountNode","backgroundNode","textHolderNode","loadingHolderNode","loadingCircleNode","loadingNumberRollingNode","freeSpinWon","startButtonSprite","freeSpinDesc","buttonHover","backEffectHolder","frontEffectHolder","bgNode","blVfxANode","blVfxBNode","blVfxC1Node","blVfxC2Node","blCharNode","blFgNode","wildParticleANode"],3,1,1,1,1,1,1,1,1,1,1,1,1,1,1,1,1,1,1,1,1,1,1,1],["6ce4aSiKeVGJZPyEX2VbsSD",["node","displayController"],3,1,1],["3142aQR/shASo2uVaU35yUL",["life","particleCount","angle","angleVar","startScaleVar","endScaleIsFactor","node","sourcePos","sourcePosVar","particlePrefab"],-3,1,5,5,6],["cc.Button",["_N$interactable","node","clickEvents","_N$normalColor","_N$target"],2,1,9,5,1],["cc.ClickEvent",["_componentId","handler","target"],1,1]],[[4,0,1,2,2],[0,0,4,5,3,6,7,2],[2,0,1,4,5,6,3],[0,0,1,4,5,3,6,7,3],[2,2,0,1,4,5,6,4],[2,0,1,4,5,3],[0,0,1,4,8,3,3],[3,0,2,3,4,5,8,6,2],[2,3,2,0,1,4,5,6,5],[6,0,2],[0,0,2,8,5,3,3],[0,0,4,8,3,2],[0,0,1,4,8,3,7,3],[0,0,4,5,3,6,2],[0,0,4,5,3,2],[0,0,1,4,5,3,6,7,9,3],[0,0,4,5,3,10,6,7,2],[3,0,1,2,7,3,4,5,6,3],[3,0,2,3,4,5,6,2],[7,0,1,2,3,2],[8,0,1,2,3,4,5,6,7,8,9,10,11,12,13,14,15,16,17,18,19,20,21,22,1],[4,1,2,1],[9,0,1,1],[5,0,1,2,3,4,5,14,6,7,8,9,10,11,12,13,15,16,17,18,17],[5,0,1,2,3,4,5,6,7,8,9,10,11,12,13,16,17,18,15],[10,0,1,2,3,4,5,6,7,8,9,7],[11,0,1,2,3,4,2],[12,0,1,2,3]],[[[{"name":"loading_circle_normal","rect":[1117,1153,162,163],"offset":[0,0],"originalSize":[162,163],"rotated":1,"capInsets":[0,0,0,0]}],[1],0,[0],[2],[1]],[[{"name":"bl_vfx_b_screen","rect":[575,603,540,600],"offset":[0,0],"originalSize":[540,600],"rotated":1,"capInsets":[0,0,0,0]}],[1],0,[0],[2],[2]],[[[9,"bonus_loading_controller"],[10,"bonus_loading_controller",false,[-25,-26,-27,-28,-29,-30],[[20,-24,-23,-22,-21,-20,-19,-18,-17,-16,-15,-14,-13,-12,-11,-10,-9,-8,-7,-6,-5,-4,-3,-2]],[21,-1,0]],[6,"back_effect_holder",0,1,[-31,-32,-33,-34,-35],[0,"27RrFLq/1Ahrj0bzKmEf6k",1,0]],[17,"start_button_holder",0,1,[-37,-38,-39],[-36],[0,"9d3FQHNh5JGpwYBNlDCozu",1,0],[5,500,125],[0,-650,0,0,0,0,1,0,0,1]],[6,"front_effect_holder",0,1,[-40,-41,-42],[0,"d6kRJ/0CFCTYPX9FCsc2up",1,0]],[11,"text_holder",4,[-43,-44,-45],[0,"12Fw+xWPFFPaYhnW3cV7N6",1,0]],[19,"loading_progress_text",[[-46,[22,-48,-47]],1,4],[0,"5cVbhee31LMbhNB61kAYmd",1,0],[5,300,200]],[1,"free_spin_count_text",5,[[23,1080,false,false,null,null,175,1.75,0,0,0,0,0,0,0,0,0,-50,-49,[16,17,18,19,20,21,22,23,24,25]]],[0,"80l1wyvztOlJ/IEsVuHPPg",1,0],[5,1080,540],[0,700,0,0,0,0,1,1,1,1]],[12,"loading_holder",0,1,[-51,6],[0,"23HouF8dRAlpZCydOQwcpS",1,0],[0,-650,0,0,0,0,1,1,1,1]],[13,"background_cover",2,[[2,0,false,-52,[0],1]],[0,"1cHBeWGB1BX6wJU1rdSBhC",1,0],[5,1080,2340]],[14,"wild_particle_a_system",2,[[25,2,50,0,0,0.25,true,-53,[0,0,50],[0,540,540],2]],[0,"6dP8rVwehAFoiLD1eS+5Wk",1,0]],[3,"bl_vfx_c_add 1",0,2,[[4,1,2,false,-54,[3],4]],[0,"96s9UX8fZA3b1jplbumeUb",1,0],[5,700,700],[0,260,0,0,0,0,1,2,2,2]],[15,"bl_vfx_c_add 2",0,2,[[4,1,2,false,-55,[5],6]],[0,"77EW2xbiNKwrBH1RFVaNxO",1,0],[5,700,700],[0,260,0,0,0,0.3826834323650898,0.9238795325112867,2,2,2],[1,0,0,45]],[3,"bl_vfx_b_screen",0,2,[[8,1,769,2,false,-56,[7],8]],[0,"3caxB8RHFP8KVEzOefGQ1R",1,0],[5,540,600],[0,260,0,0,0,0,1,2,2,1]],[3,"bl_char",0,1,[[2,2,false,-57,[9],10]],[0,"8b7jyR2ExP17P8BEisGndk",1,0],[5,711,1135],[0,-489,0,0,0,0,1,1.428,1.428,1.428]],[1,"bl_fg",4,[[2,2,false,-58,[13],14]],[0,"35WgT///5Jsol5+Vw6EZ8P",1,0],[5,756,280],[0,-880,0,0,0,0,1,2,2,2]],[3,"bl_vfx_a_add",0,1,[[4,1,2,false,-59,[27],28]],[0,"a0WDNfiZlFnoJjojadz+G/",1,0],[5,500,500],[0,500,0,0,0,0,1,12,12,12]],[1,"loading_circle_normal",8,[[2,2,false,-60,[29],30]],[0,"91l0SNP0RElYyRsCEJs3fu",1,0],[5,162,163],[0,0,0,0,0,0,1,2,2,1]],[16,"button_vfx_holder",3,[[8,1,769,2,false,-61,[43],44]],[0,"c5jTZi9z5N351Nhkrbn9pE",1,0],[4,4278190080],[5,450,230],[0,0,0,0,0,0,1,2,2,1]],[1,"glow_add",4,[[4,1,2,false,-62,[11],12]],[0,"3cJeR1/sRMVK5d08IUc3hS",1,0],[5,772,1170],[-110,145,0,0,0,0,1,2,2,2]],[7,"free_spins_text",5,[-63],[0,"481wjDlqtEh6Y1igzcpGmi",1,0],[5,652,220],[0,0.5,0],[0,225,0,0,0,0,1,1.4285714,1.4285714,1]],[5,2,false,20,[15]],[7,"free_spin_desc",5,[-64],[0,"d1kO9eloVDobOgDoW5RuZQ",1,0],[5,647,127],[0,0.5,1],[0,-150,0,0,0,0,1,1.4285714,1.4285714,1]],[5,2,false,22,[26]],[24,300,false,false,null,null,45,0,0,0,0,0,0,0,0,6,6,[31,32,33,34,35,36,37,38,39,40]],[1,"start_button",3,[[2,2,false,-65,[41],42]],[0,"43Vdo3vIlHwJr5CGROS2Eb",1,0],[5,489,175],[0,0,0,0,0,0,1,1.43,1.43,1]],[18,"start_button_text",3,[-66],[0,"f8dCjiKvVFOL705cgz8eHh",1,0],[5,162,66],[0,0,0,0,0,0,1,1.4286,1.4286,1]],[5,2,false,26,[45]],[26,false,3,[[27,"608baPWdipJ966Y0+pwFNWK","mouseClick",1]],[4,4292269782],3]],0,[0,3,1,0,4,10,0,5,15,0,6,14,0,7,12,0,8,11,0,9,13,0,10,16,0,11,9,0,12,4,0,13,2,0,14,18,0,15,23,0,16,27,0,17,21,0,18,6,0,19,17,0,20,8,0,21,5,0,22,1,0,23,7,0,24,28,0,25,3,0,0,1,0,-1,2,0,-2,14,0,-3,4,0,-4,16,0,-5,8,0,-6,3,0,-1,9,0,-2,10,0,-3,11,0,-4,12,0,-5,13,0,-1,28,0,-1,25,0,-2,18,0,-3,26,0,-1,19,0,-2,15,0,-3,5,0,-1,20,0,-2,7,0,-3,22,0,-1,24,0,26,24,0,0,6,0,27,7,0,0,7,0,-1,17,0,0,9,0,0,10,0,0,11,0,0,12,0,0,13,0,0,14,0,0,15,0,0,16,0,0,17,0,0,18,0,0,19,0,-1,21,0,-1,23,0,0,25,0,-1,27,0,28,1,6,29,8,66],[0,0,0,0,0,0,0,0,0,0,0,0,0,0,0,0,0,0,0,0,0,0,0,0,0,0,0,0,0,0,0,0,0,0,0,0,0,0,0,0,0,0,0,0,0,0,21,23,27],[-1,1,30,-1,1,-1,1,-1,1,-1,1,-1,1,-1,1,-1,-1,-2,-3,-4,-5,-6,-7,-8,-9,-10,-1,-1,1,-1,1,-1,-2,-3,-4,-5,-6,-7,-8,-9,-10,-1,1,-1,1,-1,1,1,1],[0,4,5,0,3,0,3,0,6,0,7,0,8,0,9,0,10,11,12,13,14,15,16,17,18,19,0,0,20,0,21,22,23,24,25,26,27,28,29,30,31,0,32,0,33,0,34,35,36]],[[{"name":"bl_char","rect":[1,1,699,1129],"offset":[0,-3],"originalSize":[711,1135],"capInsets":[0,0,0,0]}],[1],0,[0],[2],[1]],[[{"name":"bl_fg","rect":[702,718,756,278],"offset":[0,-1],"originalSize":[756,280],"capInsets":[0,0,0,0]}],[1],0,[0],[2],[1]],[[{"name":"bl_bg","rect":[0,0,756,1638],"offset":[0,0],"originalSize":[756,1638],"capInsets":[0,0,0,0]}],[1],0,[0],[2],[37]],[[{"name":"bl_vfx_a_add","rect":[73,633,500,500],"offset":[0,0],"originalSize":[500,500],"capInsets":[0,0,0,0]}],[1],0,[0],[2],[2]],[[{"name":"glow_add","rect":[0,0,772,1170],"offset":[0,0],"originalSize":[772,1170],"capInsets":[0,0,0,0]}],[1],0,[0],[2],[38]]]]