[1,["50C6J7c4ZKAa4h0FTgcbIc"],["_textureSetter"],["cc.SpriteFrame"],0,[[[{"name":"orangeRing_01","rect":[1423,636,290,285],"offset":[0,2],"originalSize":[354,371],"capInsets":[0,0,0,0]}],[0],0,[0],[0],[0]],[[{"name":"orangeRing_02","rect":[1,1,354,371],"offset":[0,0],"originalSize":[354,371],"capInsets":[0,0,0,0]}],[0],0,[0],[0],[0]],[[{"name":"orangeRing_05","rect":[357,374,354,371],"offset":[0,0],"originalSize":[354,371],"capInsets":[0,0,0,0]}],[0],0,[0],[0],[0]],[[{"name":"orangeRing_06","rect":[713,1,354,371],"offset":[0,0],"originalSize":[354,371],"capInsets":[0,0,0,0]}],[0],0,[0],[0],[0]],[[{"name":"orangeRing_03","rect":[1,374,354,371],"offset":[0,0],"originalSize":[354,371],"capInsets":[0,0,0,0]}],[0],0,[0],[0],[0]]]]