[1,["b7nB3l84hJEJqt3QMbEYcd"],["_textureSetter"],["cc.SpriteFrame"],0,[[[{"name":"impact_fx_02","rect":[337,1,64,64],"offset":[60,-57],"originalSize":[64,64],"capInsets":[0,0,0,0]}],[0],0,[0],[0],[0]],[[{"name":"impact_fx_00","rect":[403,1,30,32],"offset":[74,-74],"originalSize":[30,32],"rotated":1,"capInsets":[0,0,0,0]}],[0],0,[0],[0],[0]],[[{"name":"impact_fx_05","rect":[1,299,136,138],"offset":[22,-20],"originalSize":[136,138],"rotated":1,"capInsets":[0,0,0,0]}],[0],0,[0],[0],[0]],[[{"name":"impact_fx_06","rect":[141,299,134,138],"offset":[23,-19],"originalSize":[134,138],"rotated":1,"capInsets":[0,0,0,0]}],[0],0,[0],[0],[0]],[[{"name":"impact_fx_03","rect":[327,147,104,102],"offset":[38,-39],"originalSize":[104,102],"capInsets":[0,0,0,0]}],[0],0,[0],[0],[0]],[[{"name":"impact_fx_01","rect":[337,67,46,46],"offset":[68,-66],"originalSize":[46,46],"capInsets":[0,0,0,0]}],[0],0,[0],[0],[0]],[[{"name":"impact_fx_08","rect":[171,147,150,154],"offset":[17,0],"originalSize":[150,154],"rotated":1,"capInsets":[0,0,0,0]}],[0],0,[0],[0],[0]],[[{"name":"impact_fx_09","rect":[171,1,164,144],"offset":[5,-17],"originalSize":[164,144],"capInsets":[0,0,0,0]}],[0],0,[0],[0],[0]],[[{"name":"impact_fx_10","rect":[1,1,168,156],"offset":[6,-7],"originalSize":[168,156],"capInsets":[0,0,0,0]}],[0],0,[0],[0],[0]],[[{"name":"impact_fx_04","rect":[281,299,126,126],"offset":[26,-26],"originalSize":[126,126],"capInsets":[0,0,0,0]}],[0],0,[0],[0],[0]],[[{"name":"impact_fx_07","rect":[1,159,138,150],"offset":[22,-6],"originalSize":[138,150],"rotated":1,"capInsets":[0,0,0,0]}],[0],0,[0],[0],[0]]]]