[1,["4e2WhMtTtNDrAFs3Uvxx38","062SsJGONEkpJpOvXq6BDu","aeWQdBh4JERq9R0/Yx7cpf","0f8Y7ZWodCIpyUQR0p8RDN","60lNirAd9DyIL0GiunofHc","f7oK5uzG5HaZtZE+wKcFfx","e18vrsjGlIN7YH2a5CNyuK"],["_textureSetter","fb_cancel","fb_cost","fb_desc","fb_main","fb_start","fb_title"],["cc.SpriteFrame",["cc.SpriteAtlas",["_name","_spriteFrames"],2,11]],[[1,0,1,2]],[[[{"name":"fb_cancel","rect":[123,1,218,49],"offset":[0,0],"originalSize":[218,49],"rotated":1,"capInsets":[0,0,0,0]}],[0],0,[0],[0],[0]],[[{"name":"fb_desc","rect":[296,137,501,104],"offset":[0,0],"originalSize":[501,104],"capInsets":[0,0,0,0]}],[0],0,[0],[0],[0]],[[[0,"feature_buy.plist",[{},"fb_cancel",6,0,"fb_cost",6,1,"fb_desc",6,2,"fb_main",6,3,"fb_start",6,4,"fb_title",6,5]]],0,0,[0,0,0,0,0,0],[1,2,3,4,5,6],[1,2,3,4,5,6]],[[{"name":"fb_main","rect":[1,1,222,120],"offset":[0,0],"originalSize":[222,120],"rotated":1,"capInsets":[0,0,0,0]}],[0],0,[0],[0],[0]],[[{"name":"fb_cost","rect":[174,177,120,36],"offset":[0,0],"originalSize":[120,36],"capInsets":[0,0,0,0]}],[0],0,[0],[0],[0]],[[{"name":"fb_title","rect":[221,1,599,134],"offset":[0,0],"originalSize":[599,134],"capInsets":[0,0,0,0]}],[0],0,[0],[0],[0]],[[{"name":"fb_start","rect":[174,1,174,45],"offset":[0,0],"originalSize":[174,45],"rotated":1,"capInsets":[0,0,0,0]}],[0],0,[0],[0],[0]]]]